emfindus/ChipShouterInterface.py
emfindus/MachineController.py
emfindus/__init__.py
emfindus-0.9.0.dist-info/LICENSE
emfindus-0.9.0.dist-info/METADATA
emfindus-0.9.0.dist-info/WHEEL
emfindus-0.9.0.dist-info/top_level.txt
emfindus-0.9.0.dist-info/RECORD
