Metadata-Version: 2.2
Name: emfindus
Version: 0.9.0
Summary: Add-on library to findus to perform electromagnetic fault injection (emfi) attacks with the ChipSHOUTER
Author-email: Matthias Kesenheimer <matthias.kesenheimer@syss.de>, Manuel Stotz <manuel.stotz@syss.de>
License:                     GNU GENERAL PUBLIC LICENSE
Project-URL: Homepage, https://mkesenheimer.github.io
Project-URL: Documentation, https://fault-injection-library.readthedocs.io/en/latest/
License-File: LICENSE
Requires-Dist: setuptools
Requires-Dist: findus
Requires-Dist: chipshouter
Requires-Dist: pynput
Requires-Dist: more-itertools
